Core/__init__.py
gui/__init__.py
hybrides/__init__.py
serve/__init__.py
pycrossgate-0.0.0.1.dist-info/METADATA
pycrossgate-0.0.0.1.dist-info/WHEEL
pycrossgate-0.0.0.1.dist-info/entry_points.txt
pycrossgate-0.0.0.1.dist-info/top_level.txt
pycrossgate-0.0.0.1.dist-info/RECORD
